project/app.py
project/database.py
dolcera_threshold_finder-1.0.0.dist-info/LICENSE
dolcera_threshold_finder-1.0.0.dist-info/METADATA
dolcera_threshold_finder-1.0.0.dist-info/WHEEL
dolcera_threshold_finder-1.0.0.dist-info/entry_points.txt
dolcera_threshold_finder-1.0.0.dist-info/top_level.txt
dolcera_threshold_finder-1.0.0.dist-info/RECORD
