Metadata-Version: 2.1
Name: dolcera-threshold-finder
Version: 1.0.0
Summary: Dolcera threshold finder package
Home-page: UNKNOWN
Author: Pritom Hazarika
License: MIT
Platform: UNKNOWN
Classifier: License :: OSI Approved :: MIT License
Classifier: Programming Language :: Python :: 3
Classifier: Programming Language :: Python :: 3.7
Requires-Dist: requests
Requires-Dist: xml
Requires-Dist: pandas
Requires-Dist: fuzzywuzzy
Requires-Dist: psycopg2
Requires-Dist: re
